ocr_stream/__init__.py
ocr_stream/recognize.py
ocr_stream/bin_tess/__init__.py
ocr_stream/modules/__init__.py
ocr_stream/ocr/__init__.py
ocr_stream-2.5.2.dist-info/METADATA
ocr_stream-2.5.2.dist-info/WHEEL
ocr_stream-2.5.2.dist-info/top_level.txt
ocr_stream-2.5.2.dist-info/RECORD
