Metadata-Version: 2.4
Name: ocr_stream
Version: 2.5.2
Summary: Extrair textos de documentos digitalizados e imagens.
Author: Bruno Chaves
Requires-Python: >=3.11
Requires-Dist: PyMuPDF
Requires-Dist: reportlab
Requires-Dist: openpyxl
Requires-Dist: pandas
Requires-Dist: requests>=2.32.4
Requires-Dist: opencv-python
Requires-Dist: pytesseract
Requires-Dist: convert_stream>=2.5.1
Requires-Dist: soup_files>=1.4.2
